gridfanapi/__init__.py
gridfanapi/gridfanapi.py
gridfanapi/util.py
gridfanapi-1.0.0.dist-info/LICENSE
gridfanapi-1.0.0.dist-info/METADATA
gridfanapi-1.0.0.dist-info/WHEEL
gridfanapi-1.0.0.dist-info/top_level.txt
gridfanapi-1.0.0.dist-info/RECORD
